lab_4/FA_1B.v
module FA_1B(a,b,cin,cout,s);
	//all inputs and outputs are 1-bit
	input a, b, cin; 
	output reg  cout, s; 

	always @ (a or b or cin) begin 
			{cout, s} = a + b + cin; 
	end

endmodule

lab_4/FA_4B.v
module FA_4B(a,b,cin,cout,s);
	//some inputs and outputs are 1-bit, some are 4-bit

	input[3:0] a, b; 
	input cin; 

	wire[3:0] c; 
	
	output  cout; 
	output[3:0] s; 

	FA_1B first(.a(a[0]), .b(b[0]), .cin(cin), .cout(c[0]), .s(s[0]));

	genvar i; 
	generate
		for (i = 1; i < 4; i = i + 1) begin
			FA_1B fa_1b(.a(a[i]), .b(b[i]), .cin(c[i-1]), .cout(c[i]), .s(s[i]));
		end
	endgenerate

	assign cout = c[3]; 
endmodule

lab_4/L4P3_TB.v
`timescale 1ns / 1ps
module L4P3_TB;

	reg [1:0] count;
	//Add inputs/outputs
	reg[3:0] a, b; 
	wire cout; 
	wire[3:0] s;
	
	//instantiate and connect fourBit_FA
	FA_4B fa_4b(.a(a), .b(b), .cin(1'b0), .cout(cout), .s(s));
 	
	initial begin 
		$dumpfile("function.vcd");
		$dumpvars(0, L4P3_TB);
		count = 2'b00;
		#1000

		$finish;
	end
	
	always begin
		#50
		count=count+2'b01;
	end

	assign c = 1'b0; 
	
	always @(count) begin
		case (count)
		 2'b00 : begin a = 4'b0000; b = 4'b0000; end  // expect s=0000, cout=0
        2'b01 : begin a = 4'b0001; b = 4'b0010; end  // expect s=0011, cout=0
        2'b10 : begin a = 4'b0111; b = 4'b1000; end  // expect s=1111, cout=0
        2'b11 : begin a = 4'b1111; b = 4'b0001; end  // expect s=1111, cout=0
		default : begin a = 4'b0000; b = 4'b0001; end
	endcase
	end
	
endmodule

/*
	cd usyd/26s1/elec2602/lab/4/p3
	iverilog -o out.vvp FA_1B.v FA_4B.v L4P3_TB.vb


*/

lab_4/function.vcd
$date
	Mon Apr 13 15:53:01 2026
$end
$version
	Icarus Verilog
$end
$timescale
	1ps
$end
$scope module L4P3_TB $end
$var wire 1 ! c $end
$var wire 4 " s [3:0] $end
$var wire 1 # cout $end
$var reg 4 $ a [3:0] $end
$var reg 4 % b [3:0] $end
$var reg 2 & count [1:0] $end
$scope module fa_4b $end
$var wire 4 ' a [3:0] $end
$var wire 4 ( b [3:0] $end
$var wire 1 ) cin $end
$var wire 4 * s [3:0] $end
$var wire 1 # cout $end
$var wire 4 + c [3:0] $end
$scope begin genblk1[1] $end
$var parameter 2 , i $end
$scope module fa_1b $end
$var wire 1 - a $end
$var wire 1 . b $end
$var wire 1 / cin $end
$var reg 1 0 cout $end
$var reg 1 1 s $end
$upscope $end
$upscope $end
$scope begin genblk1[2] $end
$var parameter 3 2 i $end
$scope module fa_1b $end
$var wire 1 3 a $end
$var wire 1 4 b $end
$var wire 1 5 cin $end
$var reg 1 6 cout $end
$var reg 1 7 s $end
$upscope $end
$upscope $end
$scope begin genblk1[3] $end
$var parameter 3 8 i $end
$scope module fa_1b $end
$var wire 1 9 a $end
$var wire 1 : b $end
$var wire 1 ; cin $end
$var reg 1 < cout $end
$var reg 1 = s $end
$upscope $end
$upscope $end
$scope module first $end
$var wire 1 > a $end
$var wire 1 ? b $end
$var wire 1 ) cin $end
$var reg 1 @ cout $end
$var reg 1 A s $end
$upscope $end
$upscope $end
$upscope $end
$enddefinitions $end
$comment Show the parameter values. $end
$dumpall
b11 8
b10 2
b1 ,
$end
#0
$dumpvars
0A
0@
0?
0>
0=
0<
0;
0:
09
07
06
05
04
03
01
00
0/
0.
0-
b0 +
b0 *
0)
b0 (
b0 '
b0 &
b0 %
b0 $
0#
b0 "
0!
$end
#50000
11
b11 "
b11 *
1A
1.
1>
b10 %
b10 (
b1 $
b1 '
b1 &
#100000
1=
b1111 "
b1111 *
17
0.
1:
1-
13
b1000 %
b1000 (
b111 $
b111 '
b10 &
#150000
1#
1<
0=
1;
16
07
15
10
01
1/
b1111 +
1@
b0 "
b0 *
0A
0:
1?
19
b1 %
b1 (
b1111 $
b1111 '
b11 &
#200000
05
0;
0#
0/
00
01
06
07
0<
b0 "
b0 *
0=
b0 +
0@
0?
0-
03
09
0>
b0 %
b0 (
b0 $
b0 '
b0 &
#250000
11
b11 "
b11 *
1A
1.
1>
b10 %
b10 (
b1 $
b1 '
b1 &
#300000
1=
b1111 "
b1111 *
17
0.
1:
1-
13
b1000 %
b1000 (
b111 $
b111 '
b10 &
#350000
1#
1<
0=
1;
16
07
15
10
01
1/
b1111 +
1@
b0 "
b0 *
0A
0:
1?
19
b1 %
b1 (
b1111 $
b1111 '
b11 &
#400000
05
0;
0#
0/
00
01
06
07
0<
b0 "
b0 *
0=
b0 +
0@
0?
0-
03
09
0>
b0 %
b0 (
b0 $
b0 '
b0 &
#450000
11
b11 "
b11 *
1A
1.
1>
b10 %
b10 (
b1 $
b1 '
b1 &
#500000
1=
b1111 "
b1111 *
17
0.
1:
1-
13
b1000 %
b1000 (
b111 $
b111 '
b10 &
#550000
1#
1<
0=
1;
16
07
15
10
01
1/
b1111 +
1@
b0 "
b0 *
0A
0:
1?
19
b1 %
b1 (
b1111 $
b1111 '
b11 &
#600000
05
0;
0#
0/
00
01
06
07
0<
b0 "
b0 *
0=
b0 +
0@
0?
0-
03
09
0>
b0 %
b0 (
b0 $
b0 '
b0 &
#650000
11
b11 "
b11 *
1A
1.
1>
b10 %
b10 (
b1 $
b1 '
b1 &
#700000
1=
b1111 "
b1111 *
17
0.
1:
1-
13
b1000 %
b1000 (
b111 $
b111 '
b10 &
#750000
1#
1<
0=
1;
16
07
15
10
01
1/
b1111 +
1@
b0 "
b0 *
0A
0:
1?
19
b1 %
b1 (
b1111 $
b1111 '
b11 &
#800000
05
0;
0#
0/
00
01
06
07
0<
b0 "
b0 *
0=
b0 +
0@
0?
0-
03
09
0>
b0 %
b0 (
b0 $
b0 '
b0 &
#850000
11
b11 "
b11 *
1A
1.
1>
b10 %
b10 (
b1 $
b1 '
b1 &
#900000
1=
b1111 "
b1111 *
17
0.
1:
1-
13
b1000 %
b1000 (
b111 $
b111 '
b10 &
#950000
1#
1<
0=
1;
16
07
15
10
01
1/
b1111 +
1@
b0 "
b0 *
0A
0:
1?
19
b1 %
b1 (
b1111 $
b1111 '
b11 &
#1000000
05
0;
0#
0/
00
01
06
07
0<
b0 "
b0 *
0=
b0 +
0@
0?
0-
03
09
0>
b0 %
b0 (
b0 $
b0 '
b0 &
